dict_reorder/__init__.py
dict_reorder-0.1.dist-info/LICENSE
dict_reorder-0.1.dist-info/METADATA
dict_reorder-0.1.dist-info/WHEEL
dict_reorder-0.1.dist-info/top_level.txt
dict_reorder-0.1.dist-info/RECORD
