Metadata-Version: 2.1
Name: dict-reorder
Version: 0.1
Summary: A tool used to easily reorder dictionary indexes.
Home-page: https://github.com/xyzpw/dict-reorder/
Author: xyzpw
Maintainer: xyzpw
License: MIT
Keywords: dictionaries,manipulator
Classifier: Programming Language :: Python :: 3
Classifier: Programming Language :: Python :: 3.10
Classifier: Programming Language :: Python :: 3.11
Classifier: Programming Language :: Python :: 3.12
Classifier: License :: OSI Approved :: MIT License
Classifier: Intended Audience :: Developers
License-File: LICENSE
